cloudreve/__init__.py
cloudreve/models.py
cloudreve/utils.py
cloudreve/v3.py
cloudreve/v4.py
cloudreve-2.0.1.dist-info/licenses/LICENSE
cloudreve-2.0.1.dist-info/METADATA
cloudreve-2.0.1.dist-info/WHEEL
cloudreve-2.0.1.dist-info/top_level.txt
cloudreve-2.0.1.dist-info/RECORD
